README.md
flask_raml.py
setup.py
Flask_RAML.egg-info/PKG-INFO
Flask_RAML.egg-info/SOURCES.txt
Flask_RAML.egg-info/dependency_links.txt
Flask_RAML.egg-info/namespace_packages.txt
Flask_RAML.egg-info/requires.txt
Flask_RAML.egg-info/top_level.txt
Flask_RAML.egg-info/zip-safe